ftl/__init__.py
ftl/connection.py
ftl/errors.py
ftl/response.py
ftl/stream.py
ftl/utils.py
ftl-0.0.6.dist-info/DESCRIPTION.rst
ftl-0.0.6.dist-info/METADATA
ftl-0.0.6.dist-info/RECORD
ftl-0.0.6.dist-info/WHEEL
ftl-0.0.6.dist-info/metadata.json
ftl-0.0.6.dist-info/top_level.txt
