Metadata-Version: 2.0
Name: ftl
Version: 0.0.6
Summary: asyncio-based HTTP/2 implementation
Home-page: https://github.com/other-xyz/ftl
Author: Adam Rothman
Author-email: adam@other.xyz
License: Apache License 2.0
Platform: UNKNOWN
Classifier: Intended Audience :: Developers
Classifier: Programming Language :: Python
Classifier: Programming Language :: Python :: 3
Classifier: Programming Language :: Python :: 3.5
Classifier: Programming Language :: Python :: 3.6
Requires-Dist: h2
Requires-Dist: hpack
Requires-Dist: multidict
